leanpy/LSTM.py
leanpy/__init__.py
leanpy/dfClearTools.py
leanpy/get_iot_data.py
leanpy/yg_iot_api.py
leanpy/点位检测与分析工具.py
leanpy-0.0.1.dist-info/licenses/LICENSE.txt
leanpy-0.0.1.dist-info/METADATA
leanpy-0.0.1.dist-info/WHEEL
leanpy-0.0.1.dist-info/top_level.txt
leanpy-0.0.1.dist-info/RECORD
