Metadata-Version: 2.4
Name: leanpy
Version: 0.0.1
Summary: Lean Manufacturing + Python
Home-page: https://gitee.com/benxuu/lean-py
Author: Ben Xu
Author-email: benxuu@163.com
Maintainer-email: Ben Xu <benxuu@163.com>
License-Expression: MIT
Project-URL: Source, https://gitee.com/benxuu/lean-py
Classifier: Development Status :: 3 - Alpha
Classifier: Intended Audience :: Developers
Classifier: Operating System :: OS Independent
Classifier: Programming Language :: Python :: 3
Classifier: Typing :: Typed
Requires-Python: >=3.10
License-File: LICENSE.txt
Requires-Dist: numpy>=1.19.0
Dynamic: author
Dynamic: author-email
Dynamic: home-page
Dynamic: license-file
Dynamic: requires-python
